LICENSE
MANIFEST.in
README.rst
requirements.txt
setup.cfg
setup.py
PyNLPl.egg-info/PKG-INFO
PyNLPl.egg-info/SOURCES.txt
PyNLPl.egg-info/dependency_links.txt
PyNLPl.egg-info/entry_points.txt
PyNLPl.egg-info/not-zip-safe
PyNLPl.egg-info/requires.txt
PyNLPl.egg-info/top_level.txt
pynlpl/__init__.py
pynlpl/algorithms.py
pynlpl/common.py
pynlpl/datatypes.py
pynlpl/evaluation.py
pynlpl/fsa.py
pynlpl/net.py
pynlpl/search.py
pynlpl/statistics.py
pynlpl/tagger.py
pynlpl/textprocessors.py
pynlpl/clients/__init__.py
pynlpl/clients/cornetto.py
pynlpl/clients/freeling.py
pynlpl/clients/frogclient.py
pynlpl/formats/__init__.py
pynlpl/formats/cgn.py
pynlpl/formats/cql.py
pynlpl/formats/dutchsemcor.py
pynlpl/formats/folia.py
pynlpl/formats/foliaset.py
pynlpl/formats/fql.py
pynlpl/formats/giza.py
pynlpl/formats/imdi.py
pynlpl/formats/moses.py
pynlpl/formats/sonar.py
pynlpl/formats/taggerdata.py
pynlpl/formats/timbl.py
pynlpl/lm/__init__.py
pynlpl/lm/client.py
pynlpl/lm/lm.py
pynlpl/lm/server.py
pynlpl/lm/srilm.py
pynlpl/mt/__init__.py
pynlpl/mt/wordalign.py
pynlpl/tests/__init__.py
pynlpl/tests/cgn.py
pynlpl/tests/cql.py
pynlpl/tests/datatypes.py
pynlpl/tests/evaluation.py
pynlpl/tests/folia.py
pynlpl/tests/folia_benchmark.py
pynlpl/tests/formats.py
pynlpl/tests/fql.py
pynlpl/tests/search.py
pynlpl/tests/statistics.py
pynlpl/tests/test.sh
pynlpl/tests/textprocessors.py
pynlpl/tests/FoLiA/setup.py
pynlpl/tests/FoLiA/foliatools/__init__.py
pynlpl/tests/FoLiA/foliatools/alpino2folia.py
pynlpl/tests/FoLiA/foliatools/cgn2folia.py
pynlpl/tests/FoLiA/foliatools/dcoi2folia.py
pynlpl/tests/FoLiA/foliatools/folia2annotatedtxt.py
pynlpl/tests/FoLiA/foliatools/folia2columns.py
pynlpl/tests/FoLiA/foliatools/folia2dcoi.py
pynlpl/tests/FoLiA/foliatools/folia2html.py
pynlpl/tests/FoLiA/foliatools/folia2rst.py
pynlpl/tests/FoLiA/foliatools/folia2txt.py
pynlpl/tests/FoLiA/foliatools/foliacat.py
pynlpl/tests/FoLiA/foliatools/foliacorrect.py
pynlpl/tests/FoLiA/foliatools/foliacount.py
pynlpl/tests/FoLiA/foliatools/foliafreqlist.py
pynlpl/tests/FoLiA/foliatools/foliaid.py
pynlpl/tests/FoLiA/foliatools/foliamerge.py
pynlpl/tests/FoLiA/foliatools/foliaquery.py
pynlpl/tests/FoLiA/foliatools/foliaquery1.py
