Metadata-Version: 1.1
Name: PyNLPl
Version: 1.2.6
Summary: PyNLPl, pronounced as 'pineapple', is a Python library for Natural Language Processing. It contains various modules useful for common, and less common, NLP tasks. PyNLPl contains modules for basic tasks, clients for interfacting with server, and modules for parsing several file formats common in NLP, most notably FoLiA.
Home-page: https://github.com/proycon/pynlpl
Author: Maarten van Gompel
Author-email: proycon@anaproy.nl
License: GPL
Keywords: nlp computational_linguistics search ngrams language_models linguistics toolkit
Platform: UNKNOWN
Classifier: Development Status :: 5 - Production/Stable
Classifier: Topic :: Text Processing :: Linguistic
Classifier: Programming Language :: Python :: 2.7
Classifier: Programming Language :: Python :: 3
Classifier: Operating System :: POSIX
Classifier: Intended Audience :: Developers
Classifier: Intended Audience :: Science/Research
Classifier: License :: OSI Approved :: GNU General Public License v3 (GPLv3)
